seg2link/__init__.py
seg2link/_tests_r1.py
seg2link/_tests_r2.py
seg2link/boundary.py
seg2link/cache_bbox.py
seg2link/icon_small.png
seg2link/link_by_overlap.py
seg2link/message_windows_round2.py
seg2link/misc.py
seg2link/parameters.py
seg2link/seg2dlink_core.py
seg2link/seg2link_round1.py
seg2link/seg2link_round2.py
seg2link/single_cell_division.py
seg2link/start_round1.py
seg2link/start_round2.py
seg2link/start_seg2link.py
seg2link/userconfig.py
seg2link/watersheds.py
seg2link/widgets_round1.py
seg2link/widgets_round2.py
seg2link-0.1.3.dist-info/LICENSE
seg2link-0.1.3.dist-info/METADATA
seg2link-0.1.3.dist-info/WHEEL
seg2link-0.1.3.dist-info/entry_points.txt
seg2link-0.1.3.dist-info/top_level.txt
seg2link-0.1.3.dist-info/RECORD
