Metadata-Version: 2.1
Name: seg2link
Version: 0.1.3
Summary: A napari based 3D segmentation software for electron microscopy images
Home-page: https://github.com/WenChentao/Seg2Link
Author: Chentao Wen
Author-email: chintou.on@gmail.com
Classifier: Programming Language :: Python :: 3
Classifier: License :: OSI Approved :: MIT License
Classifier: Operating System :: OS Independent
Requires-Python: >=3.8
License-File: LICENSE
Requires-Dist: napari[pyqt5] (==0.4.10)
Requires-Dist: scikit-image (==0.18.3)
